fasterStringTie/__init__.py
fasterStringTie/script.py
fasterStringTie-1.3.dist-info/METADATA
fasterStringTie-1.3.dist-info/WHEEL
fasterStringTie-1.3.dist-info/entry_points.txt
fasterStringTie-1.3.dist-info/top_level.txt
fasterStringTie-1.3.dist-info/RECORD
