Metadata-Version: 2.1
Name: fasterStringTie
Version: 1.3
Summary: A three times faster version of StringTie.
Author: Waqar Hanif
License: UNKNOWN
Platform: UNKNOWN
